chinormfilter/__init__.py
chinormfilter/cli.py
chinormfilter-0.5.3.dist-info/LICENSE
chinormfilter-0.5.3.dist-info/METADATA
chinormfilter-0.5.3.dist-info/WHEEL
chinormfilter-0.5.3.dist-info/entry_points.txt
chinormfilter-0.5.3.dist-info/RECORD
